hatool_compiler/VERSION
hatool_compiler/__init__.py
hatool_compiler/compiler.py
hatool_compiler-0.0.2.dist-info/LICENSE
hatool_compiler-0.0.2.dist-info/METADATA
hatool_compiler-0.0.2.dist-info/WHEEL
hatool_compiler-0.0.2.dist-info/entry_points.txt
hatool_compiler-0.0.2.dist-info/top_level.txt
hatool_compiler-0.0.2.dist-info/RECORD
