Metadata-Version: 2.1
Name: hatool-compiler
Version: 0.0.2
Summary: Compiler for hatool, a versatile scriptable chatbot-like interface for Angular
Home-page: https://github.com/akariv/hatool-compiler
Author: Adam Kariv
Author-email: adam.kariv@gmail.com
License: MIT
Keywords: data,ui,chatbot
Platform: UNKNOWN
Classifier: Development Status :: 4 - Beta
Classifier: Intended Audience :: Developers
Classifier: License :: OSI Approved :: MIT License
Classifier: Operating System :: OS Independent
Classifier: Programming Language :: Python :: 3.6
Classifier: Topic :: Software Development :: Libraries :: Python Modules
Requires-Dist: awesome-slugify
Requires-Dist: requests
Requires-Dist: PyYAML
Provides-Extra: develop
Requires-Dist: pylama ; extra == 'develop'
Requires-Dist: tox ; extra == 'develop'
